etrobo_python/__init__.py
etrobo_python/device.py
etrobo_python/etrobo.py
etrobo_python/log.py
etrobo_python/backends/__init__.py
etrobo_python/backends/pybricks/__init__.py
etrobo_python/backends/pybricks/device.py
etrobo_python/backends/pybricks/dispatcher.py
etrobo_python/backends/raspike/__init__.py
etrobo_python/backends/raspike/connector.py
etrobo_python/backends/raspike/device.py
etrobo_python/backends/raspike/dispatcher.py
etrobo_python/backends/raspike_art/__init__.py
etrobo_python/backends/raspike_art/connector.py
etrobo_python/backends/raspike_art/device.py
etrobo_python/backends/raspike_art/dispatcher.py
etrobo_python/backends/raspyke/__init__.py
etrobo_python/backends/raspyke/connector.py
etrobo_python/backends/raspyke/device.py
etrobo_python/backends/raspyke/dispatcher.py
etrobo_python/backends/simulator/__init__.py
etrobo_python/backends/simulator/connector.py
etrobo_python/backends/simulator/device.py
etrobo_python/backends/simulator/dispatcher.py
etrobo_python-0.6.1.dist-info/LICENSE
etrobo_python-0.6.1.dist-info/METADATA
etrobo_python-0.6.1.dist-info/WHEEL
etrobo_python-0.6.1.dist-info/top_level.txt
etrobo_python-0.6.1.dist-info/RECORD
