Metadata-Version: 2.1
Name: etrobo_python
Version: 0.6.1
Summary: Python middleware for ET-ROBOCON 2025.
Home-page: https://github.com/takedarts/etrobo-python
Author: Atsushi TAKEDA
Author-email: takedarts@mail.tohoku-gakuin.ac.jp
License: MIT
Classifier: Programming Language :: Python :: 3
Classifier: License :: OSI Approved :: MIT License
Requires-Python: >=3.7
License-File: LICENSE
